amqpstorm_pool/__init__.py
amqpstorm_pool/tests/__init__.py
AMQPStorm_Pool-1.0.1.dist-info/LICENSE
AMQPStorm_Pool-1.0.1.dist-info/METADATA
AMQPStorm_Pool-1.0.1.dist-info/WHEEL
AMQPStorm_Pool-1.0.1.dist-info/top_level.txt
AMQPStorm_Pool-1.0.1.dist-info/RECORD
